LICENSE
README.md
ariadne_django_ext/__init__.py
ariadne_django_ext/cache.py
ariadne_django_ext/decorators.py
ariadne_django_ext/directives.py
ariadne_django_ext/utils.py
ariadne_django_ext-1.6.dist-info/LICENSE
ariadne_django_ext-1.6.dist-info/WHEEL
ariadne_django_ext-1.6.dist-info/METADATA
ariadne_django_ext-1.6.dist-info/RECORD
