Metadata-Version: 2.1
Name: ariadne-django-ext
Version: 1.6
Summary: Usable utility extensions for Ariadne & Django
Home-page: https://github.com/dulmandakh/ariadne-django-ext
License: MIT
Keywords: django,ariadne,cache,graphql
Author: Dulmandakh
Author-email: dulmandakh@gmail.com
Requires-Python: >=3.6.2,<4.0.0
Classifier: Environment :: Web Environment
Classifier: Framework :: Django
Classifier: Framework :: Django :: 2.2
Classifier: Framework :: Django :: 3.0
Classifier: Framework :: Django :: 3.1
Classifier: Framework :: Django :: 3.2
Classifier: Intended Audience :: Developers
Classifier: License :: OSI Approved :: MIT License
Classifier: Programming Language :: Python
Classifier: Programming Language :: Python :: 3
Classifier: Programming Language :: Python :: 3.10
Classifier: Programming Language :: Python :: 3.6
Classifier: Programming Language :: Python :: 3.7
Classifier: Programming Language :: Python :: 3.8
Classifier: Programming Language :: Python :: 3.9
Classifier: Topic :: Software Development :: Build Tools
Project-URL: Repository, https://github.com/dulmandakh/ariadne-django-ext
